pgpy/__init__.py
pgpy/_curves.py
pgpy/constants.py
pgpy/decorators.py
pgpy/errors.py
pgpy/pgp.py
pgpy/symenc.py
pgpy/types.py
pgpy/packet/__init__.py
pgpy/packet/fields.py
pgpy/packet/packets.py
pgpy/packet/types.py
pgpy/packet/subpackets/__init__.py
pgpy/packet/subpackets/signature.py
pgpy/packet/subpackets/types.py
pgpy/packet/subpackets/userattribute.py
pgpy13-0.6.1rc1.dist-info/LICENSE
pgpy13-0.6.1rc1.dist-info/METADATA
pgpy13-0.6.1rc1.dist-info/WHEEL
pgpy13-0.6.1rc1.dist-info/top_level.txt
pgpy13-0.6.1rc1.dist-info/RECORD
