Metadata-Version: 2.2
Name: PGPy13
Version: 0.6.1rc1
Summary: Pretty Good Privacy for Python (temporary fork for py3.13 compatability)
Home-page: https://github.com/memory/PGPy
Author: Nathan J. Mehl
Author-email: pypi@memory.blank.org
License: BSD-3-Clause
Project-URL: Documentation, https://pgpy.readthedocs.io/en/latest/
Project-URL: Bug Tracker, https://github.com/memory/PGPy/issues
Keywords: OpenPGP,PGP,Pretty Good Privacy,GPG,GnuPG,openpgp,pgp,gnupg,gpg,encryption,signature
Classifier: Development Status :: 4 - Beta
Classifier: Operating System :: POSIX :: Linux
Classifier: Operating System :: MacOS :: MacOS X
Classifier: Operating System :: Microsoft :: Windows
Classifier: Intended Audience :: Developers
Classifier: Programming Language :: Python
Classifier: Programming Language :: Python :: 3
Classifier: Programming Language :: Python :: 3 :: Only
Classifier: Programming Language :: Python :: 3.13
Classifier: Programming Language :: Python :: 3.12
Classifier: Programming Language :: Python :: 3.11
Classifier: Programming Language :: Python :: 3.10
Classifier: Programming Language :: Python :: 3.9
Classifier: Programming Language :: Python :: Implementation :: CPython
Classifier: Topic :: Security
Classifier: Topic :: Security :: Cryptography
Classifier: Topic :: Software Development :: Libraries
Classifier: Topic :: Software Development :: Libraries :: Python Modules
Classifier: License :: OSI Approved :: BSD License
Requires-Python: >=3.9
License-File: LICENSE
Requires-Dist: cryptography>=38.0.0
Requires-Dist: pyasn1
